SF_plum_finder/API_handling.py
SF_plum_finder/__init__.py
SF_plum_finder/__main__.py
SF_plum_finder/init_config.py
SF_plum_finder/plum_finder.py
SF_plum_finder/data/Addresses.db
SF_plum_finder/data/Plum_Street_Tree_List.pkl
SF_plum_finder/data/Street_Names.json
SF_plum_finder/data/street_types.json
SF_plum_finder-1.2.9.dist-info/LICENSE
SF_plum_finder-1.2.9.dist-info/METADATA
SF_plum_finder-1.2.9.dist-info/WHEEL
SF_plum_finder-1.2.9.dist-info/top_level.txt
SF_plum_finder-1.2.9.dist-info/RECORD
