Metadata-Version: 2.1
Name: SF-plum-finder
Version: 1.2.9
Summary: Find the closest plum in San Francisco
Author-email: Zaven Cook <zavencook@gmail.com>
License: Copyright (c) 2022 Zaven Cook
Project-URL: Homepage, https://github.com/zcook7904/plum_finder
Project-URL: Bug Tracker, https://github.com/zcook7904/plum_finder/issues
Classifier: Programming Language :: Python :: 3
Classifier: License :: OSI Approved :: MIT License
Classifier: Operating System :: OS Independent
Requires-Python: >=3.7
License-File: LICENSE
Requires-Dist: googlemaps
Requires-Dist: numpy
Requires-Dist: pandas
